README.md
setup.py
lbrlabs_pulumi_cockroach/__init__.py
lbrlabs_pulumi_cockroach/_inputs.py
lbrlabs_pulumi_cockroach/_utilities.py
lbrlabs_pulumi_cockroach/allow_list.py
lbrlabs_pulumi_cockroach/api_oidc_config.py
lbrlabs_pulumi_cockroach/ca_cert.py
lbrlabs_pulumi_cockroach/cluster.py
lbrlabs_pulumi_cockroach/cmek.py
lbrlabs_pulumi_cockroach/database.py
lbrlabs_pulumi_cockroach/finalize_version_upgrade.py
lbrlabs_pulumi_cockroach/folder.py
lbrlabs_pulumi_cockroach/get_cluster_cert.py
lbrlabs_pulumi_cockroach/get_cockroach_cluster.py
lbrlabs_pulumi_cockroach/get_connection_string.py
lbrlabs_pulumi_cockroach/get_organization.py
lbrlabs_pulumi_cockroach/get_person_user.py
lbrlabs_pulumi_cockroach/log_export_config.py
lbrlabs_pulumi_cockroach/maintenance_window.py
lbrlabs_pulumi_cockroach/metric_export_cloudwatch_config.py
lbrlabs_pulumi_cockroach/metric_export_datadog_config.py
lbrlabs_pulumi_cockroach/outputs.py
lbrlabs_pulumi_cockroach/private_endpoint_connection.py
lbrlabs_pulumi_cockroach/private_endpoint_services.py
lbrlabs_pulumi_cockroach/private_endpoint_trusted_owner.py
lbrlabs_pulumi_cockroach/provider.py
lbrlabs_pulumi_cockroach/pulumi-plugin.json
lbrlabs_pulumi_cockroach/py.typed
lbrlabs_pulumi_cockroach/sql_user.py
lbrlabs_pulumi_cockroach/user_role_grants.py
lbrlabs_pulumi_cockroach/version_deferral.py
lbrlabs_pulumi_cockroach.egg-info/PKG-INFO
lbrlabs_pulumi_cockroach.egg-info/SOURCES.txt
lbrlabs_pulumi_cockroach.egg-info/dependency_links.txt
lbrlabs_pulumi_cockroach.egg-info/not-zip-safe
lbrlabs_pulumi_cockroach.egg-info/requires.txt
lbrlabs_pulumi_cockroach.egg-info/top_level.txt
lbrlabs_pulumi_cockroach/config/__init__.py
lbrlabs_pulumi_cockroach/config/vars.py