Metadata-Version: 2.1
Name: lbrlabs-pulumi-cockroach
Version: 0.1.0
Summary: A Pulumi package to create and managed cockroach db resources in Pulumi programs.
Home-page: https://lbrlabs.com
License: Apache-2.0
Project-URL: Repository, https://github.com/lbrlabs/pulumi-cockroach
Keywords: pulumi cockroach
Platform: UNKNOWN
Requires-Python: >=3.7
